calendly/__init__.py
calendly/calendly.py
calendly/utils/constants.py
calendly/utils/requests.py
PyCalendly-1.0.0.dist-info/LICENSE
PyCalendly-1.0.0.dist-info/METADATA
PyCalendly-1.0.0.dist-info/WHEEL
PyCalendly-1.0.0.dist-info/top_level.txt
PyCalendly-1.0.0.dist-info/RECORD
