Metadata-Version: 2.1
Name: PyCalendly
Version: 1.0.0
Summary: Python wrapper for Calendly API v2
Home-page: https://github.com/laxmena/PyCalendly
Author: laxmena
Author-email: ConnectWith@laxmena.com
License: MIT
Download-URL: https://github.com/laxmena/PyCalendly
Keywords: Calendly python api v2
Platform: any
Classifier: Intended Audience :: Developers
Classifier: Topic :: Software Development
Classifier: Programming Language :: Python
Requires-Python: >3.6
License-File: LICENSE
Requires-Dist: requests
